TFL_STP/LICENSE
TFL_STP/README.rst
TFL_STP/__init__.py
TFL_STP/fs_find.py
TFL_STP/setup.cfg
TFL_STP/setup.py
TFL_STP-2.0.dist-info/LICENSE
TFL_STP-2.0.dist-info/METADATA
TFL_STP-2.0.dist-info/WHEEL
TFL_STP-2.0.dist-info/top_level.txt
TFL_STP-2.0.dist-info/RECORD
