Metadata-Version: 2.1
Name: TFL-STP
Version: 2.0
Summary: Setup helper functions for TFL-based packages
Home-page: https://github.com/Tapyr/tapyr
Author: Christian Tanzer
Author-email: tanzer@swing.co.at
License: BSD License
Platform: Any
Classifier: Development Status :: 5 - Production/Stable
Classifier: License :: OSI Approved :: BSD License
Classifier: Operating System :: OS Independent
Classifier: Programming Language :: Python
Classifier: Intended Audience :: Developers
Classifier: Topic :: Software Development :: Libraries :: Python Modules
Requires-Python: <3
